[
  {
    "Id": 0,
    "Name": "Ramirez Jr, Jim",
    "AtBats": 11,
    "Hits": 3,
    "Runs": 3,
    "Doubles": 0,
    "Triples": 0,
    "HomeRuns": 0,
    "RBIs": 2,
    "StrikeOuts": 0,
    "Sacrifces": 0,
    "BaseOnBalls": 0,
    "Attempts": 1,
    "PutOuts": 3,
    "Errors": 0,
    "InningsPitched": 18.0,
    "HitsAllowed": 95,
    "BattersOut": 2,
    "BattersWalked": 14,
    "RunsAllowed": 90,
    "EarnedRuns": 68,
    "BattingAverage": 0.273,
    "SluggingPercent": 0.273,
    "OnBasePercent": 0.273,
    "RSP": 0.250,
    "FieldingAverage": 1.000,
    "EarnedRunsAverage": 26.44
  },
  {
    "Id": 0,
    "Name": "Adams, Chris",
    "AtBats": 2,
    "Hits": 2,
    "Runs": 2,
    "Doubles": 0,
    "Triples": 0,
    "HomeRuns": 0,
    "RBIs": 0,
    "StrikeOuts": 0,
    "Sacrifces": 0,
    "BaseOnBalls": 1,
    "Attempts": 0,
    "PutOuts": 0,
    "Errors": 0,
    "InningsPitched": 0.0,
    "HitsAllowed": 0,
    "BattersOut": 0,
    "BattersWalked": 0,
    "RunsAllowed": 0,
    "EarnedRuns": 0,
    "BattingAverage": 1.000,
    "SluggingPercent": 1.000,
    "OnBasePercent": 1.000,
    "RSP": 0.000,
    "FieldingAverage": 0.000,
    "EarnedRunsAverage": 0.00
  },
  {
    "Id": 0,
    "Name": "Saunders Sr., Mike",
    "AtBats": 8,
    "Hits": 4,
    "Runs": 2,
    "Doubles": 0,
    "Triples": 0,
    "HomeRuns": 0,
    "RBIs": 2,
    "StrikeOuts": 1,
    "Sacrifces": 0,
    "BaseOnBalls": 1,
    "Attempts": 0,
    "PutOuts": 14,
    "Errors": 1,
    "InningsPitched": 0.0,
    "HitsAllowed": 0,
    "BattersOut": 0,
    "BattersWalked": 0,
    "RunsAllowed": 0,
    "EarnedRuns": 0,
    "BattingAverage": 0.500,
    "SluggingPercent": 0.500,
    "OnBasePercent": 0.667,
    "RSP": 1.000,
    "FieldingAverage": 0.933,
    "EarnedRunsAverage": 0.00
  },
  {
    "Id": 0,
    "Name": "Deaver, Glenn",
    "AtBats": 12,
    "Hits": 7,
    "Runs": 4,
    "Doubles": 2,
    "Triples": 2,
    "HomeRuns": 0,
    "RBIs": 7,
    "StrikeOuts": 0,
    "Sacrifces": 0,
    "BaseOnBalls": 1,
    "Attempts": 4,
    "PutOuts": 6,
    "Errors": 1,
    "InningsPitched": 0.0,
    "HitsAllowed": 0,
    "BattersOut": 0,
    "BattersWalked": 0,
    "RunsAllowed": 0,
    "EarnedRuns": 0,
    "BattingAverage": 0.583,
    "SluggingPercent": 1.083,
    "OnBasePercent": 0.615,
    "RSP": 0.667,
    "FieldingAverage": 0.909,
    "EarnedRunsAverage": 0.00
  },
  {
    "Id": 0,
    "Name": "Jefferson, Daniel",
    "AtBats": 5,
    "Hits": 3,
    "Runs": 2,
    "Doubles": 1,
    "Triples": 0,
    "HomeRuns": 0,
    "RBIs": 2,
    "StrikeOuts": 0,
    "Sacrifces": 0,
    "BaseOnBalls": 1,
    "Attempts": 1,
    "PutOuts": 3,
    "Errors": 0,
    "InningsPitched": 0.0,
    "HitsAllowed": 0,
    "BattersOut": 0,
    "BattersWalked": 0,
    "RunsAllowed": 0,
    "EarnedRuns": 0,
    "BattingAverage": 0.600,
    "SluggingPercent": 0.800,
    "OnBasePercent": 1.000,
    "RSP": 1.000,
    "FieldingAverage": 1.000,
    "EarnedRunsAverage": 0.00
  },
  {
    "Id": 0,
    "Name": "Sells, Ryan",
    "AtBats": 2,
    "Hits": 0,
    "Runs": 0,
    "Doubles": 0,
    "Triples": 0,
    "HomeRuns": 0,
    "RBIs": 0,
    "StrikeOuts": 0,
    "Sacrifces": 0,
    "BaseOnBalls": 0,
    "Attempts": 0,
    "PutOuts": 1,
    "Errors": 0,
    "InningsPitched": 0.0,
    "HitsAllowed": 0,
    "BattersOut": 0,
    "BattersWalked": 0,
    "RunsAllowed": 0,
    "EarnedRuns": 0,
    "BattingAverage": 0.000,
    "SluggingPercent": 0.000,
    "OnBasePercent": 0.000,
    "RSP": 0.000,
    "FieldingAverage": 1.000,
    "EarnedRunsAverage": 0.00
  },
  {
    "Id": 0,
    "Name": "Gonzales, Joey",
    "AtBats": 6,
    "Hits": 3,
    "Runs": 2,
    "Doubles": 0,
    "Triples": 1,
    "HomeRuns": 0,
    "RBIs": 2,
    "StrikeOuts": 0,
    "Sacrifces": 0,
    "BaseOnBalls": 0,
    "Attempts": 5,
    "PutOuts": 3,
    "Errors": 2,
    "InningsPitched": 0.0,
    "HitsAllowed": 0,
    "BattersOut": 0,
    "BattersWalked": 0,
    "RunsAllowed": 0,
    "EarnedRuns": 0,
    "BattingAverage": 0.500,
    "SluggingPercent": 0.833,
    "OnBasePercent": 0.500,
    "RSP": 0.333,
    "FieldingAverage": 0.800,
    "EarnedRunsAverage": 0.00
  },
  {
    "Id": 0,
    "Name": "Labonte, Andre",
    "AtBats": 8,
    "Hits": 3,
    "Runs": 2,
    "Doubles": 1,
    "Triples": 0,
    "HomeRuns": 0,
    "RBIs": 3,
    "StrikeOuts": 0,
    "Sacrifces": 1,
    "BaseOnBalls": 0,
    "Attempts": 2,
    "PutOuts": 5,
    "Errors": 2,
    "InningsPitched": 0.0,
    "HitsAllowed": 0,
    "BattersOut": 0,
    "BattersWalked": 0,
    "RunsAllowed": 0,
    "EarnedRuns": 0,
    "BattingAverage": 0.375,
    "SluggingPercent": 0.500,
    "OnBasePercent": 0.333,
    "RSP": 0.400,
    "FieldingAverage": 0.778,
    "EarnedRunsAverage": 0.00
  },
  {
    "Id": 0,
    "Name": "Donde, Ben",
    "AtBats": 7,
    "Hits": 4,
    "Runs": 2,
    "Doubles": 1,
    "Triples": 0,
    "HomeRuns": 0,
    "RBIs": 3,
    "StrikeOuts": 0,
    "Sacrifces": 0,
    "BaseOnBalls": 0,
    "Attempts": 1,
    "PutOuts": 5,
    "Errors": 1,
    "InningsPitched": 0.0,
    "HitsAllowed": 0,
    "BattersOut": 0,
    "BattersWalked": 0,
    "RunsAllowed": 0,
    "EarnedRuns": 0,
    "BattingAverage": 0.571,
    "SluggingPercent": 0.714,
    "OnBasePercent": 0.571,
    "RSP": 0.400,
    "FieldingAverage": 0.857,
    "EarnedRunsAverage": 0.00
  },
  {
    "Id": 0,
    "Name": "Brown, Joe",
    "AtBats": 6,
    "Hits": 1,
    "Runs": 1,
    "Doubles": 0,
    "Triples": 0,
    "HomeRuns": 0,
    "RBIs": 0,
    "StrikeOuts": 0,
    "Sacrifces": 0,
    "BaseOnBalls": 0,
    "Attempts": 0,
    "PutOuts": 5,
    "Errors": 0,
    "InningsPitched": 0.0,
    "HitsAllowed": 0,
    "BattersOut": 0,
    "BattersWalked": 0,
    "RunsAllowed": 0,
    "EarnedRuns": 0,
    "BattingAverage": 0.167,
    "SluggingPercent": 0.167,
    "OnBasePercent": 0.167,
    "RSP": 0.000,
    "FieldingAverage": 1.000,
    "EarnedRunsAverage": 0.00
  },
  {
    "Id": 0,
    "Name": "Ramirez Iii, James",
    "AtBats": 3,
    "Hits": 2,
    "Runs": 1,
    "Doubles": 0,
    "Triples": 0,
    "HomeRuns": 1,
    "RBIs": 2,
    "StrikeOuts": 0,
    "Sacrifces": 0,
    "BaseOnBalls": 1,
    "Attempts": 0,
    "PutOuts": 0,
    "Errors": 0,
    "InningsPitched": 0.0,
    "HitsAllowed": 0,
    "BattersOut": 0,
    "BattersWalked": 0,
    "RunsAllowed": 0,
    "EarnedRuns": 0,
    "BattingAverage": 0.667,
    "SluggingPercent": 1.667,
    "OnBasePercent": 0.750,
    "RSP": 1.000,
    "FieldingAverage": 0.000,
    "EarnedRunsAverage": 0.00
  },
  {
    "Id": 0,
    "Name": "Saunders Jr., Michael",
    "AtBats": 9,
    "Hits": 6,
    "Runs": 5,
    "Doubles": 0,
    "Triples": 1,
    "HomeRuns": 3,
    "RBIs": 7,
    "StrikeOuts": 0,
    "Sacrifces": 0,
    "BaseOnBalls": 1,
    "Attempts": 0,
    "PutOuts": 1,
    "Errors": 1,
    "InningsPitched": 0.0,
    "HitsAllowed": 0,
    "BattersOut": 0,
    "BattersWalked": 0,
    "RunsAllowed": 0,
    "EarnedRuns": 0,
    "BattingAverage": 0.667,
    "SluggingPercent": 1.889,
    "OnBasePercent": 0.700,
    "RSP": 0.750,
    "FieldingAverage": 0.500,
    "EarnedRunsAverage": 0.00
  },
  {
    "Id": 0,
    "Name": "Nguyen, Vu",
    "AtBats": 7,
    "Hits": 3,
    "Runs": 1,
    "Doubles": 0,
    "Triples": 0,
    "HomeRuns": 0,
    "RBIs": 1,
    "StrikeOuts": 0,
    "Sacrifces": 0,
    "BaseOnBalls": 0,
    "Attempts": 0,
    "PutOuts": 2,
    "Errors": 0,
    "InningsPitched": 0.0,
    "HitsAllowed": 0,
    "BattersOut": 0,
    "BattersWalked": 0,
    "RunsAllowed": 0,
    "EarnedRuns": 0,
    "BattingAverage": 0.429,
    "SluggingPercent": 0.429,
    "OnBasePercent": 0.429,
    "RSP": 0.000,
    "FieldingAverage": 1.000,
    "EarnedRunsAverage": 0.00
  },
  {
    "Id": 0,
    "Name": "Hess, Matt",
    "AtBats": 11,
    "Hits": 5,
    "Runs": 4,
    "Doubles": 0,
    "Triples": 0,
    "HomeRuns": 0,
    "RBIs": 0,
    "StrikeOuts": 0,
    "Sacrifces": 0,
    "BaseOnBalls": 1,
    "Attempts": 5,
    "PutOuts": 6,
    "Errors": 5,
    "InningsPitched": 0.0,
    "HitsAllowed": 0,
    "BattersOut": 0,
    "BattersWalked": 0,
    "RunsAllowed": 0,
    "EarnedRuns": 0,
    "BattingAverage": 0.455,
    "SluggingPercent": 0.455,
    "OnBasePercent": 0.500,
    "RSP": 0.667,
    "FieldingAverage": 0.688,
    "EarnedRunsAverage": 0.00
  },
  {
    "Id": 0,
    "Name": "Mcdermott, Doug",
    "AtBats": 4,
    "Hits": 0,
    "Runs": 1,
    "Doubles": 0,
    "Triples": 0,
    "HomeRuns": 0,
    "RBIs": 0,
    "StrikeOuts": 0,
    "Sacrifces": 0,
    "BaseOnBalls": 1,
    "Attempts": 0,
    "PutOuts": 1,
    "Errors": 0,
    "InningsPitched": 0.0,
    "HitsAllowed": 0,
    "BattersOut": 0,
    "BattersWalked": 0,
    "RunsAllowed": 0,
    "EarnedRuns": 0,
    "BattingAverage": 0.000,
    "SluggingPercent": 0.000,
    "OnBasePercent": 0.200,
    "RSP": 0.000,
    "FieldingAverage": 1.000,
    "EarnedRunsAverage": 0.00
  },
  {
    "Id": 0,
    "Name": "Pickup, Player1",
    "AtBats": 4,
    "Hits": 2,
    "Runs": 1,
    "Doubles": 0,
    "Triples": 0,
    "HomeRuns": 0,
    "RBIs": 1,
    "StrikeOuts": 0,
    "Sacrifces": 0,
    "BaseOnBalls": 0,
    "Attempts": 0,
    "PutOuts": 0,
    "Errors": 1,
    "InningsPitched": 0.0,
    "HitsAllowed": 0,
    "BattersOut": 0,
    "BattersWalked": 0,
    "RunsAllowed": 0,
    "EarnedRuns": 0,
    "BattingAverage": 0.500,
    "SluggingPercent": 0.500,
    "OnBasePercent": 0.500,
    "RSP": 1.000,
    "FieldingAverage": 0.000,
    "EarnedRunsAverage": 0.00
  }
]